[
  {
    "name": "TestFlight账户管理",
    "desc": "自动存储/合并多个TestFlight账户列表, 并可导出/分享TestFlight APP.⚠️该脚本已经与\"TF区域限制解除脚本\"合并，如需使用该脚本请务必禁用它，否则可能出现APP安装异常",
    "url": "https://raw.githubusercontent.com/Infatuation-Fei/rule/main/Stash/Script/TestFlight%E8%B4%A6%E6%88%B7%E7%AE%A1%E7%90%86/TestFlightAccount.stoverride",
    "owner": "Infatuation-Fei",
    "repo": "rule"
  },
  {
    "name": " iRingo for Siri & Search",
    "desc": "(BETA for Stash 2.0) 全面自定义「Siri与搜索」的功能。注：该覆写包含代理规则。",
    "url": "https://raw.githubusercontent.com/VirgilClyne/iRingo/main/stoverride/Siri.beta.stoverride",
    "owner": "VirgilClyne",
    "repo": "iRingo"
  },
  {
    "name": " iRingo for News",
    "desc": "(BETA for Stash 2.0) 1.自定义解锁News的地区 2.Coming Soon… 注：该覆写包含代理规则，使用过程中gateway.icloud.com会走与News相同的代理线路。",
    "url": "https://raw.githubusercontent.com/VirgilClyne/iRingo/main/stoverride/News.beta.stoverride",
    "owner": "VirgilClyne",
    "repo": "iRingo"
  }
]